langchain_cratedb/__init__.py
langchain_cratedb/cache.py
langchain_cratedb/chat_history.py
langchain_cratedb/loaders.py
langchain_cratedb/patches.py
langchain_cratedb/py.typed
langchain_cratedb/retrievers.py
langchain_cratedb/vectorstores/__init__.py
langchain_cratedb/vectorstores/main.py
langchain_cratedb/vectorstores/model.py
langchain_cratedb/vectorstores/multi.py
langchain_cratedb-0.2.0.dist-info/LICENSE
langchain_cratedb-0.2.0.dist-info/METADATA
langchain_cratedb-0.2.0.dist-info/WHEEL
langchain_cratedb-0.2.0.dist-info/RECORD
